{"stats":{"minecraft:picked_up":{"minecraft:stone_sword":15,"minecraft:bone":255,"minecraft:rotten_flesh":127,"minecraft:gold_nugget":125,"minecraft:netherite_sword":1,"minecraft:gold_ingot":64,"minecraft:golden_sword":7,"minecraft:wither_skeleton_skull":64,"minecraft:blaze_rod":64,"minecraft:coal":125},"minecraft:custom":{"minecraft:time_since_rest":1,"minecraft:play_one_minute":15376940,"minecraft:walk_one_cm":351,"minecraft:damage_taken":405520,"minecraft:deaths":1,"minecraft:mob_kills":458228,"minecraft:damage_dealt":9974990,"minecraft:leave_game":4,"minecraft:time_since_death":1},"minecraft:killed":{"minecraft:zombie":122,"minecraft:wither_skeleton":204336,"minecraft:zombified_piglin":102010,"minecraft:chicken":33,"minecraft:blaze":142940},"minecraft:used":{"minecraft:netherite_sword":110617}},"DataVersion":2578}